dask_deltasharing/__init__.py
dask_deltasharing/dask_deltasharing.py
dask_deltasharing-0.0.3.dist-info/METADATA
dask_deltasharing-0.0.3.dist-info/WHEEL
dask_deltasharing-0.0.3.dist-info/RECORD
