Metadata-Version: 2.1
Name: dask_deltasharing
Version: 0.0.3
Summary: A library for accessing tables from Delta Sharing as Dask DataFrames
Project-URL: Homepage, https://github.com/KatanaGraph/dask_deltasharing
Project-URL: Bug Tracker, https://github.com/KatanaGraph/dask_deltasharing/issues
Classifier: License :: OSI Approved :: Apache Software License
Classifier: Operating System :: OS Independent
Classifier: Programming Language :: Python :: 3
Requires-Python: >=3.7
Requires-Dist: dask
Requires-Dist: delta-sharing
